learner_py.libs/libgomp-e985bcbb.so.1.0.0
pylearner/__init__.py
pylearner/dlearner.py
pylearner/learner_ext.cpython-39-x86_64-linux-gnu.so
learner_py-1.0.4.dist-info/METADATA
learner_py-1.0.4.dist-info/WHEEL
learner_py-1.0.4.dist-info/top_level.txt
learner_py-1.0.4.dist-info/RECORD
learner_py-1.0.4.dist-info/licenses/LICENSE
