Metadata-Version: 2.4
Name: learner-py
Version: 1.0.4
Summary: Implements transfer learning methods for low-rank matrix estimation.
Author: Sean McGrath, Ryan ODea, Cenhao Zhu, and Rui Duan
Maintainer: Sean McGrath
Maintainer-email: ryan.odea@psi.ch
License-File: LICENSE
Requires-Dist: numpy>=1.15
Requires-Dist: pandas>=1.0
Requires-Dist: pybind11>=2.6.0
Requires-Dist: screenot>=0.0.2
Dynamic: author
Dynamic: description
Dynamic: description-content-type
Dynamic: license-file
Dynamic: maintainer
Dynamic: maintainer-email
Dynamic: requires-dist
Dynamic: summary
